Metadata-Version: 2.1
Name: text-highlighter
Version: 0.0.15
Summary: Streamlit component for text highlighting
Home-page: https://github.com/kevin91nl/text-highlighter
Author: K.M.J. Jacobs
Author-email: mail@kevinjacobs.nl
Requires-Python: >=3.6
License-File: LICENSE
Requires-Dist: streamlit >=0.63
